LICENSE
noglobal_magic/__init__.py
noglobal_magic/core.py
noglobal_magic-0.1.3.dist-info/LICENSE
noglobal_magic-0.1.3.dist-info/WHEEL
noglobal_magic-0.1.3.dist-info/METADATA
noglobal_magic-0.1.3.dist-info/RECORD
