Metadata-Version: 2.1
Name: noglobal-magic
Version: 0.1.3
Summary: magic command for prohibit using global variables in Jupyter Notebook
Home-page: https://github.com/tokusumi/noglobal-magic
License: MIT
Keywords: jupyter-notebook
Author: tokusumi
Author-email: tksmtoms@gmail.com
Requires-Python: >=3.7
Classifier: License :: OSI Approved :: MIT License
Classifier: Operating System :: OS Independent
Classifier: Programming Language :: Python :: 3
Classifier: Programming Language :: Python :: 3 :: Only
Classifier: Programming Language :: Python :: 3.6
Classifier: Programming Language :: Python :: 3.7
Classifier: Programming Language :: Python :: 3.8
Requires-Dist: ipython (>=5.5)
Requires-Dist: pyflakes (>=2)
Project-URL: Repository, https://github.com/tokusumi/noglobal-magic
